skvectors/__init__.py
skvectors/cartesian_2d_vectors.py
skvectors/cartesian_3d_vectors.py
skvectors/cartesian_vectors.py
skvectors/fundamental_vectors.py
skvectors/helper_functions.py
skvectors/make_tolerant.py
skvectors/simple_vectors.py
skvectors/tolerant_cartesian_2d_vectors.py
skvectors/tolerant_cartesian_3d_vectors.py
skvectors/tolerant_cartesian_vectors.py
skvectors/tolerant_versatile_vectors.py
skvectors/vectors.py
skvectors/versatile_vectors.py
skvectors/doc/Using_a_Cartesian_2D_Vector_Class.ipynb
skvectors/doc/Using_a_Cartesian_2D_Vector_Class.pdf
skvectors/doc/Using_a_Cartesian_3D_Vector_Class.ipynb
skvectors/doc/Using_a_Cartesian_3D_Vector_Class.pdf
skvectors/doc/Using_a_Cartesian_Vector_Class.ipynb
skvectors/doc/Using_a_Cartesian_Vector_Class.pdf
skvectors/doc/Using_a_Fundamental_Vector_Class.ipynb
skvectors/doc/Using_a_Fundamental_Vector_Class.pdf
skvectors/doc/Using_a_Simple_Vector_Class.ipynb
skvectors/doc/Using_a_Simple_Vector_Class.pdf
skvectors/doc/Using_a_Tolerant_Cartesian_2D_Vector_Class.ipynb
skvectors/doc/Using_a_Tolerant_Cartesian_2D_Vector_Class.pdf
skvectors/doc/Using_a_Tolerant_Cartesian_3D_Vector_Class.ipynb
skvectors/doc/Using_a_Tolerant_Cartesian_3D_Vector_Class.pdf
skvectors/doc/Using_a_Tolerant_Cartesian_Vector_Class.ipynb
skvectors/doc/Using_a_Tolerant_Cartesian_Vector_Class.pdf
skvectors/doc/Using_a_Vector_Class.ipynb
skvectors/doc/Using_a_Vector_Class.pdf
skvectors/doc/.ipynb_checkpoints/Using_a_Vector_Class-checkpoint.ipynb
skvectors/tests/__init__.py
skvectors/tests/test_cartesian_2d_vector_methods_2d.py
skvectors/tests/test_cartesian_3d_vector_methods_3d.py
skvectors/tests/test_cartesian_vector_methods_3d.py
skvectors/tests/test_create_vector_classes.py
skvectors/tests/test_fundamental_vector_methods_3d.py
skvectors/tests/test_simple_vector_methods_3d.py
skvectors/tests/test_tolerant_cartesian_vector_methods_4d.py
skvectors/tests/test_vector_methods_3d.py
scikit_vectors-0.6.5.dist-info/LICENSE
scikit_vectors-0.6.5.dist-info/METADATA
scikit_vectors-0.6.5.dist-info/WHEEL
scikit_vectors-0.6.5.dist-info/top_level.txt
scikit_vectors-0.6.5.dist-info/RECORD
